mediathekview_change_downloads_to_http/__init__.py
mediathekview_change_downloads_to_http-2018.06.16.1.dist-info/DESCRIPTION.rst
mediathekview_change_downloads_to_http-2018.06.16.1.dist-info/METADATA
mediathekview_change_downloads_to_http-2018.06.16.1.dist-info/RECORD
mediathekview_change_downloads_to_http-2018.06.16.1.dist-info/WHEEL
mediathekview_change_downloads_to_http-2018.06.16.1.dist-info/entry_points.txt
mediathekview_change_downloads_to_http-2018.06.16.1.dist-info/metadata.json
mediathekview_change_downloads_to_http-2018.06.16.1.dist-info/top_level.txt
