Metadata-Version: 2.0
Name: mediathekview-change-downloads-to-http
Version: 2018.06.16.1
Summary: Modify pending MediathekView download URLs from https to http
Home-page: https://github.com/novoid/mediathekview_change_downloads_to_http
Author: Karl Voit
Author-email: tools@Karl-Voit.at
License: UNKNOWN
Download-URL: https://github.com/novoid/mediathekview_change_downloads_to_http/zipball/master
Keywords: ORF,downloads,workaround,MediathekView
Platform: UNKNOWN
Classifier: Programming Language :: Python :: 3 :: Only
Classifier: Development Status :: 5 - Production/Stable
Classifier: Environment :: Console
Classifier: Intended Audience :: End Users/Desktop
Classifier: License :: OSI Approved :: GNU General Public License (GPL)
Classifier: Operating System :: OS Independent
Requires-Dist: shutil
